pipfromrepl
